graedin_cline/__init__.py
graedin_cline/async_client.py
graedin_cline/client.py
graedin_cline/exceptions.py
graedin_cline/models.py
graedin_cline/version.py
graedin_cline_sdk-0.1.0.dist-info/METADATA
graedin_cline_sdk-0.1.0.dist-info/WHEEL
graedin_cline_sdk-0.1.0.dist-info/licenses/LICENSE
graedin_cline_sdk-0.1.0.dist-info/RECORD
