Metadata-Version: 2.4
Name: graedin-cline-sdk
Version: 0.1.0
Summary: Official Python SDK for Graedin Cline - LLM Security Firewall
Project-URL: Homepage, https://github.com/jdpahl122/graedin-cline
Project-URL: Documentation, https://github.com/jdpahl122/graedin-cline#readme
Project-URL: Repository, https://github.com/jdpahl122/graedin-cline
Project-URL: Issues, https://github.com/jdpahl122/graedin-cline/issues
Author-email: Jake Pahl <jdpahl122@gmail.com>
License: MIT
License-File: LICENSE
Keywords: ai,firewall,langchain,llm,openai,prompt-injection,prompt-security,security
Classifier: Development Status :: 4 - Beta
Classifier: Intended Audience :: Developers
Classifier: License :: OSI Approved :: MIT License
Classifier: Programming Language :: Python :: 3
Classifier: Programming Language :: Python :: 3.8
Classifier: Programming Language :: Python :: 3.9
Classifier: Programming Language :: Python :: 3.10
Classifier: Programming Language :: Python :: 3.11
Classifier: Programming Language :: Python :: 3.12
Classifier: Topic :: Security
Classifier: Topic :: Software Development :: Libraries :: Python Modules
Classifier: Typing :: Typed
Requires-Python: >=3.8
Requires-Dist: httpx>=0.25.0
Requires-Dist: pydantic>=2.0.0
Requires-Dist: requests>=2.31.0
Provides-Extra: dev
Requires-Dist: mypy>=1.0.0; extra == 'dev'
Requires-Dist: pytest-asyncio>=0.21.0; extra == 'dev'
Requires-Dist: pytest-cov>=4.0.0; extra == 'dev'
Requires-Dist: pytest-mock>=3.12.0; extra == 'dev'
Requires-Dist: pytest>=7.4.0; extra == 'dev'
Requires-Dist: ruff>=0.1.0; extra == 'dev'
